midaxusers/__init__.py
midaxusers/config.py
midaxusers/domains.py
midaxusers/migration_types.py
midaxusers/models.py
midaxusers/routes.py
midaxusers-2.0.38.dist-info/METADATA
midaxusers-2.0.38.dist-info/RECORD
midaxusers-2.0.38.dist-info/WHEEL
midaxusers-2.0.38.dist-info/entry_points.txt
midaxusers-2.0.38.dist-info/top_level.txt
midaxusersutils/__init__.py
midaxusersutils/manage.py
midaxusersutils/migrations/README
midaxusersutils/migrations/alembic.ini
midaxusersutils/migrations/env.py
midaxusersutils/migrations/script.py.mako
midaxusersutils/migrations/__pycache__/env.cpython-36.pyc
midaxusersutils/migrations/versions/427f14007618_.py
midaxusersutils/migrations/versions/f3806782e4b8_.py
midaxusersutils/migrations/versions/__pycache__/02634cd9ad64_.cpython-36.pyc
midaxusersutils/migrations/versions/__pycache__/07ca8e2da238_.cpython-36.pyc
midaxusersutils/migrations/versions/__pycache__/0c366a5dae0f_.cpython-36.pyc
midaxusersutils/migrations/versions/__pycache__/25720b6d2081_.cpython-36.pyc
midaxusersutils/migrations/versions/__pycache__/35e79bfb4edd_.cpython-36.pyc
midaxusersutils/migrations/versions/__pycache__/427f14007618_.cpython-36.pyc
midaxusersutils/migrations/versions/__pycache__/43a3450ebe27_.cpython-36.pyc
midaxusersutils/migrations/versions/__pycache__/7c38e4dbbeb3_.cpython-36.pyc
midaxusersutils/migrations/versions/__pycache__/95a6db51f87c_.cpython-36.pyc
midaxusersutils/migrations/versions/__pycache__/9895ef2d3275_.cpython-36.pyc
midaxusersutils/migrations/versions/__pycache__/9a8c2fa38f9f_.cpython-36.pyc
midaxusersutils/migrations/versions/__pycache__/a2223828c901_.cpython-36.pyc
midaxusersutils/migrations/versions/__pycache__/c2bf8576c79f_.cpython-36.pyc
midaxusersutils/migrations/versions/__pycache__/de1d81904e29_.cpython-36.pyc
midaxusersutils/migrations/versions/__pycache__/e7dd5d1c9592_.cpython-36.pyc
midaxusersutils/migrations/versions/__pycache__/ec3ceb9112aa_.cpython-36.pyc
midaxusersutils/migrations/versions/__pycache__/f3806782e4b8_.cpython-36.pyc
