Metadata-Version: 2.1
Name: midaxusers
Version: 2.0.38
Summary: Midax Users API
Home-page: http://www.midax.com
Maintainer: Midax
Maintainer-email: alex.r@midax.com
License: BSD
Platform: UNKNOWN
Requires-Dist: flask
Requires-Dist: alembic (==1.0.0)
Requires-Dist: astroid
Requires-Dist: attrs
Requires-Dist: click
Requires-Dist: colorama
Requires-Dist: Flask
Requires-Dist: Flask-HTTPAuth
Requires-Dist: Flask-Migrate
Requires-Dist: Flask-SQLAlchemy
Requires-Dist: isort
Requires-Dist: itsdangerous
Requires-Dist: Jinja2
Requires-Dist: lazy-object-proxy
Requires-Dist: Mako
Requires-Dist: MarkupSafe
Requires-Dist: mccabe
Requires-Dist: pluggy
Requires-Dist: py
Requires-Dist: pylint
Requires-Dist: pyodbc
Requires-Dist: python-dateutil
Requires-Dist: python-editor
Requires-Dist: six
Requires-Dist: SQLAlchemy
Requires-Dist: Werkzeug
Requires-Dist: wrapt
Requires-Dist: cx-Oracle
